calyx_lib/__init__.py
calyx_lib/constants.py
calyx_lib/logger.py
calyx_lib/online_player.py
calyx_lib/query.py
calyx_lib/typing.py
calyx_lib/utils.py
calyx_lib/config/__init__.py
calyx_lib/config/pydantic.py
calyx_lib/config/yaml.py
calyx_lib/interface/__init__.py
calyx_lib/interface/blossom_base_interface.py
calyx_lib/lang/en_us.yml
calyx_lib/lang/zh_cn.yml
calyx_lib/translation/__init__.py
calyx_lib/translation/text.py
calyx_lib/translation/translator.py
calyx_lib-0.1.0a4.dist-info/licenses/LICENSE
calyx_lib-0.1.0a4.dist-info/METADATA
calyx_lib-0.1.0a4.dist-info/WHEEL
calyx_lib-0.1.0a4.dist-info/top_level.txt
calyx_lib-0.1.0a4.dist-info/RECORD
