Metadata-Version: 2.4
Name: calyx_lib
Version: 0.1.0a4
Summary: Alternative MCDReforged API for MCDR plugins that requires running in other environments
Home-page: https://github.com/Lazy-Bing-Server/CalyxLib-Python
Author: Ra1ny_Yuki
Author-email: ra1ny_yuki@outlook.com
Classifier: License :: OSI Approved :: GNU Lesser General Public License v3 (LGPLv3)
Classifier: Operating System :: OS Independent
Classifier: Programming Language :: Python
Classifier: Programming Language :: Python :: 3
Classifier: Programming Language :: Python :: 3.9
Classifier: Programming Language :: Python :: 3.10
Classifier: Programming Language :: Python :: 3.11
Classifier: Programming Language :: Python :: 3.12
Classifier: Programming Language :: Python :: 3.13
License-File: LICENSE
Requires-Dist: mcdreforged>=2.13.0
Requires-Dist: pydantic>=2.0.0
Requires-Dist: colorama
Requires-Dist: colorlog
Requires-Dist: mypy_extensions
Dynamic: author
Dynamic: author-email
Dynamic: classifier
Dynamic: description
Dynamic: description-content-type
Dynamic: home-page
Dynamic: license-file
Dynamic: requires-dist
Dynamic: summary
